{
  "id": "3686678",
  "name": "no name",
  "font_family": "iconfont",
  "css_prefix_text": "icon-",
  "description": "",
  "glyphs": [
    {
      "icon_id": "1305476",
      "name": "链接",
      "font_class": "lianjie",
      "unicode": "e63f",
      "unicode_decimal": 58943
    },
    {
      "icon_id": "2823684",
      "name": "坐标",
      "font_class": "zuobiao",
      "unicode": "e65c",
      "unicode_decimal": 58972
    },
    {
      "icon_id": "11859280",
      "name": "大楼",
      "font_class": "dalou",
      "unicode": "e60d",
      "unicode_decimal": 58893
    },
    {
      "icon_id": "19446213",
      "name": "推特",
      "font_class": "twitter",
      "unicode": "ea90",
      "unicode_decimal": 60048
    },
    {
      "icon_id": "1638283",
      "name": "右箭头",
      "font_class": "youjiantou",
      "unicode": "e612",
      "unicode_decimal": 58898
    }
  ]
}
